setup.py
jsonv/ExprParser.py
jsonv/JsonParser.py
jsonv/JsonValidator.py
jsonv/__init__.py
jsonv/my_tokenizer.py
jsonv/nfa.py
jsonv.egg-info/PKG-INFO
jsonv.egg-info/SOURCES.txt
jsonv.egg-info/dependency_links.txt
jsonv.egg-info/top_level.txt