Metadata-Version: 1.0
Name: jsonv
Version: 1.0.0
Summary: JSON validator with EBNF grammar
Home-page: https://bitbucket.org/jodier/jsonv/
Author: Jerome Odier
Author-email: jerome.odier@lpsc.in2p3.fr
License: CeCILL-C
Download-URL: https://bitbucket.org/jodier/jsonv/get/master.tar.gz
Platform: UNKNOWN
